gitkritik2/cli/__init__.py
gitkritik2/cli/display.py
gitkritik2/cli/main.py
gitkritik2/core/__init__.py
gitkritik2/core/config.py
gitkritik2/core/constants.py
gitkritik2/core/diff_utils.py
gitkritik2/core/llm_interface.py
gitkritik2/core/llms/__init__.py
gitkritik2/core/llms/claude_llm.py
gitkritik2/core/llms/gemini_llm.py
gitkritik2/core/llms/local_llm.py
gitkritik2/core/llms/openai_llm.py
gitkritik2/core/models.py
gitkritik2/core/tools.py
gitkritik2/core/utils.py
gitkritik2/graph/__init__.py
gitkritik2/graph/build_graph.py
gitkritik2/nodes/__init__.py
gitkritik2/nodes/agents/__init__.py
gitkritik2/nodes/agents/bug_agent.py
gitkritik2/nodes/agents/context_agent.py
gitkritik2/nodes/agents/design_agent.py
gitkritik2/nodes/agents/style_agent.py
gitkritik2/nodes/agents/summary_agent.py
gitkritik2/nodes/detect_changes.py
gitkritik2/nodes/detect_ci_context.py
gitkritik2/nodes/format_output.py
gitkritik2/nodes/init_state.py
gitkritik2/nodes/merge_results.py
gitkritik2/nodes/post_inline.py
gitkritik2/nodes/post_inline_new.py
gitkritik2/nodes/post_summary.py
gitkritik2/nodes/prepare_context.py
gitkritik2/nodes/resolve_context.py
gitkritik2/platform/github.py
gitkritik2/platform/gitlab.py
gitkritik-0.2.1.dist-info/entry_points.txt
gitkritik-0.2.1.dist-info/METADATA
gitkritik-0.2.1.dist-info/WHEEL
gitkritik-0.2.1.dist-info/RECORD
