Metadata-Version: 2.3
Name: gitkritik
Version: 0.2.1
Summary: AI-powered code review CLI and CI agent for Git, using Langchain and LangGraph.
License: MIT
Author: Preslav Penev
Author-email: preslaff@gmail.com
Requires-Python: >=3.10,<4.0
Classifier: Development Status :: 3 - Alpha
Classifier: Environment :: Console
Classifier: Intended Audience :: Developers
Classifier: License :: OSI Approved :: MIT License
Classifier: Operating System :: OS Independent
Classifier: Programming Language :: Python :: 3
Classifier: Programming Language :: Python :: 3.10
Classifier: Programming Language :: Python :: 3.11
Classifier: Programming Language :: Python :: 3.12
Classifier: Programming Language :: Python :: 3.13
Classifier: Topic :: Software Development :: Quality Assurance
Classifier: Topic :: Software Development :: Version Control :: Git
Requires-Dist: gh (>=0.0.4,<0.0.5)
Requires-Dist: jedi (>=0.19.1,<0.20.0)
Requires-Dist: langchain (>=0.3.0,<0.4.0)
Requires-Dist: langchain-anthropic (>=0.3.0,<0.4.0)
Requires-Dist: langchain-community (>=0.3.0,<0.4.0)
Requires-Dist: langchain-core (>=0.3.52,<0.4.0)
Requires-Dist: langchain-google-genai (>=2.1.3,<3.0.0)
Requires-Dist: langchain-openai (>=0.3.0,<0.4.0)
Requires-Dist: langgraph (>=0.2.0,<0.3.0)
Requires-Dist: pydantic (>=2.5.0,<3.0.0)
Requires-Dist: python-dotenv (>=1.0.0,<2.0.0)
Requires-Dist: pyyaml (>=6.0,<7.0)
Requires-Dist: requests (>=2.31.0,<3.0.0)
Requires-Dist: rich (>=13.7.0,<14.0.0)
Requires-Dist: typer[rich] (>=0.9.0,<0.10.0)
Requires-Dist: unidiff (>=0.7.5,<0.8.0)
Project-URL: Homepage, https://github.com/your-username/gitkritik
Project-URL: Repository, https://github.com/your-username/gitkritik
